{
	"name": "32",
	"layers": [
		{
			"name": "background",
			"overriden": 0,
			"subLayers": [],
			"instances": [
				{
					"type": "TiledBackground",
					"properties": {
						"initially-visible": true,
						"origin": "top",
						"wrap-horizontal": "repeat",
						"wrap-vertical": "clamp-to-edge",
						"image-offset-x": 0,
						"image-offset-y": 0,
						"image-scale-x": 1,
						"image-scale-y": 1,
						"image-angle": 0
					},
					"uid": 2187,
					"instanceVariables": {},
					"behaviors": {},
					"world": {
						"x": 571,
						"y": 98,
						"width": 2250,
						"height": 990,
						"originX": 0.5,
						"originY": 0,
						"color": [
							1,
							1,
							1,
							0.5
						],
						"angle": 0,
						"zElevation": 0
					}
				}
			],
			"sid": 789224513639107,
			"effectTypes": [],
			"isInitiallyVisible": true,
			"isInitiallyInteractive": true,
			"color": [
				1,
				1,
				1,
				1
			],
			"backgroundColor": [
				0.8666666666666667,
				0.9725490196078431,
				1,
				1
			],
			"isTransparent": false,
			"parallaxX": 0.3,
			"parallaxY": 0.03119996643066405,
			"scaleRate": 1,
			"forceOwnTexture": false,
			"renderingMode": "3d",
			"drawOrder": "z-order",
			"useRenderCells": true,
			"blendMode": "normal",
			"zElevation": 0,
			"global": false
		},
		{
			"name": "decor",
			"overriden": 0,
			"subLayers": [],
			"instances": [
				{
					"type": "decor",
					"properties": {
						"initially-visible": true,
						"initial-animation": "Animation 1",
						"initial-frame": 8,
						"enable-collisions": false,
						"live-preview": false
					},
					"uid": 2188,
					"instanceVariables": {},
					"behaviors": {
						"Physics": {
							"properties": {
								"immovable": true,
								"collision-mask": "use-collision-polygon",
								"prevent-rotation": false,
								"density": 1,
								"friction": 0.5,
								"elasticity": 0.2,
								"linear-damping": 0,
								"angular-damping": 0.01,
								"bullet": false,
								"enabled": false
							}
						}
					},
					"world": {
						"x": 149.68869941841368,
						"y": 404.1257795242851,
						"width": 38.43270675896586,
						"height": 30.813020308932145,
						"originX": 0.5,
						"originY": 0.5,
						"color": [
							1,
							1,
							1,
							1
						],
						"angle": 0.2713652842804884,
						"zElevation": 0
					}
				},
				{
					"type": "decor",
					"properties": {
						"initially-visible": true,
						"initial-animation": "Animation 1",
						"initial-frame": 2,
						"enable-collisions": false,
						"live-preview": false
					},
					"uid": 2755,
					"instanceVariables": {},
					"behaviors": {
						"Physics": {
							"properties": {
								"immovable": true,
								"collision-mask": "use-collision-polygon",
								"prevent-rotation": false,
								"density": 1,
								"friction": 0.5,
								"elasticity": 0.2,
								"linear-damping": 0,
								"angular-damping": 0.01,
								"bullet": false,
								"enabled": false
							}
						}
					},
					"world": {
						"x": 543,
						"y": 276,
						"width": 74.92285623543934,
						"height": 48.238003329666434,
						"originX": 0.5,
						"originY": 0.5,
						"color": [
							1,
							1,
							1,
							1
						],
						"angle": 0,
						"zElevation": 0
					}
				},
				{
					"type": "decor",
					"properties": {
						"initially-visible": true,
						"initial-animation": "Animation 1",
						"initial-frame": 2,
						"enable-collisions": false,
						"live-preview": false
					},
					"uid": 2756,
					"instanceVariables": {},
					"behaviors": {
						"Physics": {
							"properties": {
								"immovable": true,
								"collision-mask": "use-collision-polygon",
								"prevent-rotation": false,
								"density": 1,
								"friction": 0.5,
								"elasticity": 0.2,
								"linear-damping": 0,
								"angular-damping": 0.01,
								"bullet": false,
								"enabled": false
							}
						}
					},
					"world": {
						"x": 882.1666666666666,
						"y": 203.50000000000003,
						"width": 74.92285623543934,
						"height": 48.238003329666434,
						"originX": 0.5,
						"originY": 0.5,
						"color": [
							1,
							1,
							1,
							1
						],
						"angle": 0,
						"zElevation": 0
					}
				},
				{
					"type": "decor",
					"properties": {
						"initially-visible": true,
						"initial-animation": "Animation 1",
						"initial-frame": 2,
						"enable-collisions": false,
						"live-preview": false
					},
					"uid": 2757,
					"instanceVariables": {},
					"behaviors": {
						"Physics": {
							"properties": {
								"immovable": true,
								"collision-mask": "use-collision-polygon",
								"prevent-rotation": false,
								"density": 1,
								"friction": 0.5,
								"elasticity": 0.2,
								"linear-damping": 0,
								"angular-damping": 0.01,
								"bullet": false,
								"enabled": false
							}
						}
					},
					"world": {
						"x": 83,
						"y": 409,
						"width": 74.92285623543934,
						"height": 48.238003329666434,
						"originX": 0.5,
						"originY": 0.5,
						"color": [
							1,
							1,
							1,
							1
						],
						"angle": 0,
						"zElevation": 0
					}
				}
			],
			"sid": 977451779132810,
			"effectTypes": [],
			"isInitiallyVisible": true,
			"isInitiallyInteractive": true,
			"color": [
				1,
				1,
				1,
				1
			],
			"backgroundColor": [
				1,
				1,
				1,
				1
			],
			"isTransparent": true,
			"parallaxX": 1,
			"parallaxY": 1,
			"scaleRate": 1,
			"forceOwnTexture": false,
			"renderingMode": "3d",
			"drawOrder": "z-order",
			"useRenderCells": true,
			"blendMode": "normal",
			"zElevation": 0,
			"global": false
		},
		{
			"name": "terrain",
			"overriden": 0,
			"subLayers": [],
			"instances": [],
			"sid": 218903029458452,
			"effectTypes": [],
			"isInitiallyVisible": true,
			"isInitiallyInteractive": true,
			"color": [
				1,
				1,
				1,
				1
			],
			"backgroundColor": [
				1,
				1,
				1,
				1
			],
			"isTransparent": true,
			"parallaxX": 1,
			"parallaxY": 1,
			"scaleRate": 1,
			"forceOwnTexture": false,
			"renderingMode": "3d",
			"drawOrder": "z-order",
			"useRenderCells": true,
			"blendMode": "normal",
			"zElevation": 0,
			"global": false
		},
		{
			"name": "base",
			"overriden": 0,
			"subLayers": [],
			"instances": [
				{
					"type": "player",
					"properties": {
						"initially-visible": true,
						"initial-animation": "default",
						"initial-frame": 0,
						"enable-collisions": true,
						"live-preview": false
					},
					"uid": 2189,
					"instanceVariables": {
						"is_current_player": true
					},
					"behaviors": {
						"Timer": {
							"properties": {}
						},
						"Physics": {
							"properties": {
								"immovable": false,
								"collision-mask": "use-collision-polygon",
								"prevent-rotation": false,
								"density": 1,
								"friction": 30,
								"elasticity": 0.2,
								"linear-damping": 0.35,
								"angular-damping": 0.35,
								"bullet": true,
								"enabled": true
							}
						},
						"Tween": {
							"properties": {
								"enabled": true
							}
						},
						"Fade": {
							"properties": {
								"fade-in-time": 0,
								"wait-time": 0,
								"fade-out-time": 1,
								"destroy": true,
								"enabled": false,
								"live-preview": false
							}
						}
					},
					"effects": {
						"Grayscale": {
							"isEnabled": true,
							"parameters": {
								"intensity": 0
							}
						}
					},
					"world": {
						"x": 88,
						"y": 395,
						"width": 33,
						"height": 39,
						"originX": 0.5,
						"originY": 0.5,
						"color": [
							1,
							1,
							1,
							1
						],
						"angle": 0,
						"zElevation": 0
					}
				},
				{
					"type": "flag",
					"properties": {
						"initially-visible": true,
						"initial-animation": "Animation 1",
						"initial-frame": 0,
						"enable-collisions": true,
						"live-preview": false
					},
					"uid": 2190,
					"instanceVariables": {},
					"behaviors": {
						"Sine": {
							"properties": {
								"movement": "vertical",
								"wave": "sine",
								"period": 2,
								"period-random": 1,
								"period-offset": 0,
								"period-offset-random": 0,
								"magnitude": 2,
								"magnitude-random": 0,
								"enabled": true,
								"live-preview": false
							}
						},
						"Fade": {
							"properties": {
								"fade-in-time": 0,
								"wait-time": 0,
								"fade-out-time": 0.2,
								"destroy": false,
								"enabled": false,
								"live-preview": false
							}
						},
						"Tween": {
							"properties": {
								"enabled": true
							}
						}
					},
					"world": {
						"x": 1170,
						"y": 90,
						"width": 35.04197287813481,
						"height": 37.49491097960425,
						"originX": 0.5,
						"originY": 0.5,
						"color": [
							1,
							1,
							1,
							1
						],
						"angle": 0,
						"zElevation": 0
					}
				},
				{
					"type": "tile",
					"properties": {
						"initially-visible": true,
						"initial-animation": "Earth",
						"initial-frame": 12,
						"enable-collisions": true,
						"live-preview": false
					},
					"uid": 2197,
					"instanceVariables": {},
					"behaviors": {
						"Physics": {
							"properties": {
								"immovable": true,
								"collision-mask": "use-collision-polygon",
								"prevent-rotation": false,
								"density": 1,
								"friction": 0.5,
								"elasticity": 0.2,
								"linear-damping": 0,
								"angular-damping": 0.01,
								"bullet": false,
								"enabled": true
							}
						}
					},
					"world": {
						"x": 21.58707083740549,
						"y": 415.2321268803481,
						"width": 45,
						"height": 45,
						"originX": 0,
						"originY": 0,
						"color": [
							1,
							1,
							1,
							1
						],
						"angle": 0,
						"zElevation": 0
					}
				},
				{
					"type": "tile",
					"properties": {
						"initially-visible": true,
						"initial-animation": "Earth",
						"initial-frame": 13,
						"enable-collisions": true,
						"live-preview": false
					},
					"uid": 2199,
					"instanceVariables": {},
					"behaviors": {
						"Physics": {
							"properties": {
								"immovable": true,
								"collision-mask": "use-collision-polygon",
								"prevent-rotation": false,
								"density": 1,
								"friction": 0.5,
								"elasticity": 0.2,
								"linear-damping": 0,
								"angular-damping": 0.01,
								"bullet": false,
								"enabled": true
							}
						}
					},
					"world": {
						"x": 66.58707083740549,
						"y": 415.2321268803481,
						"width": 45,
						"height": 45,
						"originX": 0,
						"originY": 0,
						"color": [
							1,
							1,
							1,
							1
						],
						"angle": 0,
						"zElevation": 0
					}
				},
				{
					"type": "tile",
					"properties": {
						"initially-visible": true,
						"initial-animation": "Earth",
						"initial-frame": 14,
						"enable-collisions": true,
						"live-preview": false
					},
					"uid": 2205,
					"instanceVariables": {},
					"behaviors": {
						"Physics": {
							"properties": {
								"immovable": true,
								"collision-mask": "use-collision-polygon",
								"prevent-rotation": false,
								"density": 1,
								"friction": 0.5,
								"elasticity": 0.2,
								"linear-damping": 0,
								"angular-damping": 0.01,
								"bullet": false,
								"enabled": true
							}
						}
					},
					"world": {
						"x": 111.58707083740549,
						"y": 415.2321268803481,
						"width": 45,
						"height": 45,
						"originX": 0,
						"originY": 0,
						"color": [
							1,
							1,
							1,
							1
						],
						"angle": 0,
						"zElevation": 0
					}
				},
				{
					"type": "star",
					"properties": {
						"initially-visible": true,
						"initial-animation": "stars",
						"initial-frame": 0,
						"enable-collisions": true,
						"live-preview": false
					},
					"uid": 2706,
					"instanceVariables": {
						"is_taken": false,
						"startX": 0,
						"startY": 0
					},
					"behaviors": {
						"Tween": {
							"properties": {
								"enabled": true
							}
						},
						"Sine": {
							"properties": {
								"movement": "angle",
								"wave": "sine",
								"period": 1,
								"period-random": 1,
								"period-offset": 0,
								"period-offset-random": 0,
								"magnitude": 2,
								"magnitude-random": 2,
								"enabled": true,
								"live-preview": false
							}
						}
					},
					"world": {
						"x": 1125,
						"y": 90,
						"width": 30,
						"height": 30,
						"originX": 0.5,
						"originY": 0.5,
						"color": [
							1,
							1,
							1,
							1
						],
						"angle": 0,
						"zElevation": 0
					}
				},
				{
					"type": "box",
					"properties": {
						"initially-visible": true,
						"initial-animation": "metal",
						"initial-frame": 0,
						"enable-collisions": true,
						"live-preview": false
					},
					"uid": 2728,
					"instanceVariables": {
						"impactSound": "metal"
					},
					"behaviors": {
						"Physics": {
							"properties": {
								"immovable": true,
								"collision-mask": "use-collision-polygon",
								"prevent-rotation": false,
								"density": 1,
								"friction": 0.5,
								"elasticity": 0.2,
								"linear-damping": 0,
								"angular-damping": 0.01,
								"bullet": false,
								"enabled": true
							}
						},
						"Sine": {
							"properties": {
								"movement": "horizontal",
								"wave": "sine",
								"period": 4,
								"period-random": 0,
								"period-offset": 0,
								"period-offset-random": 0,
								"magnitude": 50,
								"magnitude-random": 0,
								"enabled": false,
								"live-preview": false
							}
						}
					},
					"world": {
						"x": 495,
						"y": 315,
						"width": 45,
						"height": 45,
						"originX": 0.5,
						"originY": 0.5,
						"color": [
							1,
							1,
							1,
							1
						],
						"angle": 0,
						"zElevation": 0
					}
				},
				{
					"type": "box",
					"properties": {
						"initially-visible": true,
						"initial-animation": "metal",
						"initial-frame": 0,
						"enable-collisions": true,
						"live-preview": false
					},
					"uid": 2729,
					"instanceVariables": {
						"impactSound": "metal"
					},
					"behaviors": {
						"Physics": {
							"properties": {
								"immovable": true,
								"collision-mask": "use-collision-polygon",
								"prevent-rotation": false,
								"density": 1,
								"friction": 0.5,
								"elasticity": 0.2,
								"linear-damping": 0,
								"angular-damping": 0.01,
								"bullet": false,
								"enabled": true
							}
						},
						"Sine": {
							"properties": {
								"movement": "horizontal",
								"wave": "sine",
								"period": 4,
								"period-random": 0,
								"period-offset": 0,
								"period-offset-random": 0,
								"magnitude": 50,
								"magnitude-random": 0,
								"enabled": false,
								"live-preview": false
							}
						}
					},
					"world": {
						"x": 540,
						"y": 315,
						"width": 45,
						"height": 45,
						"originX": 0.5,
						"originY": 0.5,
						"color": [
							1,
							1,
							1,
							1
						],
						"angle": 0,
						"zElevation": 0
					}
				},
				{
					"type": "box",
					"properties": {
						"initially-visible": true,
						"initial-animation": "metal",
						"initial-frame": 0,
						"enable-collisions": true,
						"live-preview": false
					},
					"uid": 2739,
					"instanceVariables": {
						"impactSound": "metal"
					},
					"behaviors": {
						"Physics": {
							"properties": {
								"immovable": true,
								"collision-mask": "use-collision-polygon",
								"prevent-rotation": false,
								"density": 1,
								"friction": 0.5,
								"elasticity": 0.2,
								"linear-damping": 0,
								"angular-damping": 0.01,
								"bullet": false,
								"enabled": true
							}
						},
						"Sine": {
							"properties": {
								"movement": "horizontal",
								"wave": "sine",
								"period": 4,
								"period-random": 0,
								"period-offset": 0,
								"period-offset-random": 0,
								"magnitude": 50,
								"magnitude-random": 0,
								"enabled": false,
								"live-preview": false
							}
						}
					},
					"world": {
						"x": 585,
						"y": 315,
						"width": 45,
						"height": 45,
						"originX": 0.5,
						"originY": 0.5,
						"color": [
							1,
							1,
							1,
							1
						],
						"angle": 0,
						"zElevation": 0
					}
				},
				{
					"type": "box",
					"properties": {
						"initially-visible": true,
						"initial-animation": "metal",
						"initial-frame": 0,
						"enable-collisions": true,
						"live-preview": false
					},
					"uid": 2741,
					"instanceVariables": {
						"impactSound": "metal"
					},
					"behaviors": {
						"Physics": {
							"properties": {
								"immovable": true,
								"collision-mask": "use-collision-polygon",
								"prevent-rotation": false,
								"density": 1,
								"friction": 0.5,
								"elasticity": 0.2,
								"linear-damping": 0,
								"angular-damping": 0.01,
								"bullet": false,
								"enabled": true
							}
						},
						"Sine": {
							"properties": {
								"movement": "horizontal",
								"wave": "sine",
								"period": 4,
								"period-random": 0,
								"period-offset": 0,
								"period-offset-random": 0,
								"magnitude": 50,
								"magnitude-random": 0,
								"enabled": false,
								"live-preview": false
							}
						}
					},
					"world": {
						"x": 855,
						"y": 225,
						"width": 45,
						"height": 45,
						"originX": 0.5,
						"originY": 0.5,
						"color": [
							1,
							1,
							1,
							1
						],
						"angle": 0,
						"zElevation": 0
					}
				},
				{
					"type": "box",
					"properties": {
						"initially-visible": true,
						"initial-animation": "metal",
						"initial-frame": 0,
						"enable-collisions": true,
						"live-preview": false
					},
					"uid": 2743,
					"instanceVariables": {
						"impactSound": "metal"
					},
					"behaviors": {
						"Physics": {
							"properties": {
								"immovable": true,
								"collision-mask": "use-collision-polygon",
								"prevent-rotation": false,
								"density": 1,
								"friction": 0.5,
								"elasticity": 0.2,
								"linear-damping": 0,
								"angular-damping": 0.01,
								"bullet": false,
								"enabled": true
							}
						},
						"Sine": {
							"properties": {
								"movement": "horizontal",
								"wave": "sine",
								"period": 4,
								"period-random": 0,
								"period-offset": 0,
								"period-offset-random": 0,
								"magnitude": 50,
								"magnitude-random": 0,
								"enabled": false,
								"live-preview": false
							}
						}
					},
					"world": {
						"x": 900,
						"y": 225,
						"width": 45,
						"height": 45,
						"originX": 0.5,
						"originY": 0.5,
						"color": [
							1,
							1,
							1,
							1
						],
						"angle": 0,
						"zElevation": 0
					}
				},
				{
					"type": "box",
					"properties": {
						"initially-visible": true,
						"initial-animation": "metal",
						"initial-frame": 0,
						"enable-collisions": true,
						"live-preview": false
					},
					"uid": 2744,
					"instanceVariables": {
						"impactSound": "metal"
					},
					"behaviors": {
						"Physics": {
							"properties": {
								"immovable": true,
								"collision-mask": "use-collision-polygon",
								"prevent-rotation": false,
								"density": 1,
								"friction": 0.5,
								"elasticity": 0.2,
								"linear-damping": 0,
								"angular-damping": 0.01,
								"bullet": false,
								"enabled": true
							}
						},
						"Sine": {
							"properties": {
								"movement": "horizontal",
								"wave": "sine",
								"period": 4,
								"period-random": 0,
								"period-offset": 0,
								"period-offset-random": 0,
								"magnitude": 50,
								"magnitude-random": 0,
								"enabled": false,
								"live-preview": false
							}
						}
					},
					"world": {
						"x": 945,
						"y": 225,
						"width": 45,
						"height": 45,
						"originX": 0.5,
						"originY": 0.5,
						"color": [
							1,
							1,
							1,
							1
						],
						"angle": 0,
						"zElevation": 0
					}
				},
				{
					"type": "star",
					"properties": {
						"initially-visible": true,
						"initial-animation": "stars",
						"initial-frame": 0,
						"enable-collisions": true,
						"live-preview": false
					},
					"uid": 2748,
					"instanceVariables": {
						"is_taken": false,
						"startX": 0,
						"startY": 0
					},
					"behaviors": {
						"Tween": {
							"properties": {
								"enabled": true
							}
						},
						"Sine": {
							"properties": {
								"movement": "angle",
								"wave": "sine",
								"period": 1,
								"period-random": 1,
								"period-offset": 0,
								"period-offset-random": 0,
								"magnitude": 2,
								"magnitude-random": 2,
								"enabled": true,
								"live-preview": false
							}
						}
					},
					"world": {
						"x": 900,
						"y": 180,
						"width": 30,
						"height": 30,
						"originX": 0.5,
						"originY": 0.5,
						"color": [
							1,
							1,
							1,
							1
						],
						"angle": 0,
						"zElevation": 0
					}
				},
				{
					"type": "star",
					"properties": {
						"initially-visible": true,
						"initial-animation": "stars",
						"initial-frame": 0,
						"enable-collisions": true,
						"live-preview": false
					},
					"uid": 2749,
					"instanceVariables": {
						"is_taken": false,
						"startX": 0,
						"startY": 0
					},
					"behaviors": {
						"Tween": {
							"properties": {
								"enabled": true
							}
						},
						"Sine": {
							"properties": {
								"movement": "angle",
								"wave": "sine",
								"period": 1,
								"period-random": 1,
								"period-offset": 0,
								"period-offset-random": 0,
								"magnitude": 2,
								"magnitude-random": 2,
								"enabled": true,
								"live-preview": false
							}
						}
					},
					"world": {
						"x": 540,
						"y": 270,
						"width": 30,
						"height": 30,
						"originX": 0.5,
						"originY": 0.5,
						"color": [
							1,
							1,
							1,
							1
						],
						"angle": 0,
						"zElevation": 0
					}
				},
				{
					"type": "star",
					"properties": {
						"initially-visible": true,
						"initial-animation": "stars",
						"initial-frame": 0,
						"enable-collisions": true,
						"live-preview": false
					},
					"uid": 2750,
					"instanceVariables": {
						"is_taken": false,
						"startX": 0,
						"startY": 0
					},
					"behaviors": {
						"Tween": {
							"properties": {
								"enabled": true
							}
						},
						"Sine": {
							"properties": {
								"movement": "angle",
								"wave": "sine",
								"period": 1,
								"period-random": 1,
								"period-offset": 0,
								"period-offset-random": 0,
								"magnitude": 2,
								"magnitude-random": 2,
								"enabled": true,
								"live-preview": false
							}
						}
					},
					"world": {
						"x": 135,
						"y": 360,
						"width": 30,
						"height": 30,
						"originX": 0.5,
						"originY": 0.5,
						"color": [
							1,
							1,
							1,
							1
						],
						"angle": 0,
						"zElevation": 0
					}
				},
				{
					"type": "star",
					"properties": {
						"initially-visible": true,
						"initial-animation": "stars",
						"initial-frame": 0,
						"enable-collisions": true,
						"live-preview": false
					},
					"uid": 2751,
					"instanceVariables": {
						"is_taken": false,
						"startX": 0,
						"startY": 0
					},
					"behaviors": {
						"Tween": {
							"properties": {
								"enabled": true
							}
						},
						"Sine": {
							"properties": {
								"movement": "angle",
								"wave": "sine",
								"period": 1,
								"period-random": 1,
								"period-offset": 0,
								"period-offset-random": 0,
								"magnitude": 2,
								"magnitude-random": 2,
								"enabled": true,
								"live-preview": false
							}
						}
					},
					"world": {
						"x": 190.87962962962965,
						"y": 324.25925925925935,
						"width": 30,
						"height": 30,
						"originX": 0.5,
						"originY": 0.5,
						"color": [
							1,
							1,
							1,
							1
						],
						"angle": 0,
						"zElevation": 0
					}
				},
				{
					"type": "star",
					"properties": {
						"initially-visible": true,
						"initial-animation": "stars",
						"initial-frame": 0,
						"enable-collisions": true,
						"live-preview": false
					},
					"uid": 2752,
					"instanceVariables": {
						"is_taken": false,
						"startX": 0,
						"startY": 0
					},
					"behaviors": {
						"Tween": {
							"properties": {
								"enabled": true
							}
						},
						"Sine": {
							"properties": {
								"movement": "angle",
								"wave": "sine",
								"period": 1,
								"period-random": 1,
								"period-offset": 0,
								"period-offset-random": 0,
								"magnitude": 2,
								"magnitude-random": 2,
								"enabled": true,
								"live-preview": false
							}
						}
					},
					"world": {
						"x": 250.32407407407405,
						"y": 284.32870370370364,
						"width": 30,
						"height": 30,
						"originX": 0.5,
						"originY": 0.5,
						"color": [
							1,
							1,
							1,
							1
						],
						"angle": 0,
						"zElevation": 0
					}
				},
				{
					"type": "box",
					"properties": {
						"initially-visible": true,
						"initial-animation": "metal",
						"initial-frame": 0,
						"enable-collisions": true,
						"live-preview": false
					},
					"uid": 2753,
					"instanceVariables": {
						"impactSound": "metal"
					},
					"behaviors": {
						"Physics": {
							"properties": {
								"immovable": false,
								"collision-mask": "use-collision-polygon",
								"prevent-rotation": false,
								"density": 1,
								"friction": 0.5,
								"elasticity": 0.2,
								"linear-damping": 0,
								"angular-damping": 0.01,
								"bullet": false,
								"enabled": true
							}
						},
						"Sine": {
							"properties": {
								"movement": "vertical",
								"wave": "sine",
								"period": 2,
								"period-random": 0,
								"period-offset": 0,
								"period-offset-random": 1,
								"magnitude": 80,
								"magnitude-random": 1,
								"enabled": true,
								"live-preview": false
							}
						}
					},
					"world": {
						"x": 720,
						"y": 315,
						"width": 45,
						"height": 45,
						"originX": 0.5,
						"originY": 0.5,
						"color": [
							1,
							1,
							1,
							1
						],
						"angle": 0,
						"zElevation": 0
					}
				},
				{
					"type": "box",
					"properties": {
						"initially-visible": true,
						"initial-animation": "metal",
						"initial-frame": 0,
						"enable-collisions": true,
						"live-preview": false
					},
					"uid": 2754,
					"instanceVariables": {
						"impactSound": "metal"
					},
					"behaviors": {
						"Physics": {
							"properties": {
								"immovable": false,
								"collision-mask": "use-collision-polygon",
								"prevent-rotation": false,
								"density": 1,
								"friction": 0.5,
								"elasticity": 0.2,
								"linear-damping": 0,
								"angular-damping": 0.01,
								"bullet": false,
								"enabled": true
							}
						},
						"Sine": {
							"properties": {
								"movement": "vertical",
								"wave": "sine",
								"period": 2,
								"period-random": 0,
								"period-offset": 0,
								"period-offset-random": 1,
								"magnitude": 80,
								"magnitude-random": 1,
								"enabled": true,
								"live-preview": false
							}
						}
					},
					"world": {
						"x": 1035,
						"y": 180,
						"width": 45,
						"height": 45,
						"originX": 0.5,
						"originY": 0.5,
						"color": [
							1,
							1,
							1,
							1
						],
						"angle": 0,
						"zElevation": 0
					}
				},
				{
					"type": "tile",
					"properties": {
						"initially-visible": true,
						"initial-animation": "Earth",
						"initial-frame": 12,
						"enable-collisions": true,
						"live-preview": false
					},
					"uid": 2745,
					"instanceVariables": {},
					"behaviors": {
						"Physics": {
							"properties": {
								"immovable": true,
								"collision-mask": "use-collision-polygon",
								"prevent-rotation": false,
								"density": 1,
								"friction": 0.5,
								"elasticity": 0.2,
								"linear-damping": 0,
								"angular-damping": 0.01,
								"bullet": false,
								"enabled": true
							}
						}
					},
					"world": {
						"x": 1092,
						"y": 109,
						"width": 45,
						"height": 45,
						"originX": 0,
						"originY": 0,
						"color": [
							1,
							1,
							1,
							1
						],
						"angle": 0,
						"zElevation": 0
					}
				},
				{
					"type": "tile",
					"properties": {
						"initially-visible": true,
						"initial-animation": "Earth",
						"initial-frame": 13,
						"enable-collisions": true,
						"live-preview": false
					},
					"uid": 2746,
					"instanceVariables": {},
					"behaviors": {
						"Physics": {
							"properties": {
								"immovable": true,
								"collision-mask": "use-collision-polygon",
								"prevent-rotation": false,
								"density": 1,
								"friction": 0.5,
								"elasticity": 0.2,
								"linear-damping": 0,
								"angular-damping": 0.01,
								"bullet": false,
								"enabled": true
							}
						}
					},
					"world": {
						"x": 1137,
						"y": 109,
						"width": 45,
						"height": 45,
						"originX": 0,
						"originY": 0,
						"color": [
							1,
							1,
							1,
							1
						],
						"angle": 0,
						"zElevation": 0
					}
				},
				{
					"type": "tile",
					"properties": {
						"initially-visible": true,
						"initial-animation": "Earth",
						"initial-frame": 14,
						"enable-collisions": true,
						"live-preview": false
					},
					"uid": 2747,
					"instanceVariables": {},
					"behaviors": {
						"Physics": {
							"properties": {
								"immovable": true,
								"collision-mask": "use-collision-polygon",
								"prevent-rotation": false,
								"density": 1,
								"friction": 0.5,
								"elasticity": 0.2,
								"linear-damping": 0,
								"angular-damping": 0.01,
								"bullet": false,
								"enabled": true
							}
						}
					},
					"world": {
						"x": 1182,
						"y": 109,
						"width": 45,
						"height": 45,
						"originX": 0,
						"originY": 0,
						"color": [
							1,
							1,
							1,
							1
						],
						"angle": 0,
						"zElevation": 0
					}
				}
			],
			"sid": 906998088544895,
			"effectTypes": [],
			"isInitiallyVisible": true,
			"isInitiallyInteractive": true,
			"color": [
				1,
				1,
				1,
				1
			],
			"backgroundColor": [
				1,
				1,
				1,
				1
			],
			"isTransparent": true,
			"parallaxX": 1,
			"parallaxY": 1,
			"scaleRate": 1,
			"forceOwnTexture": false,
			"renderingMode": "3d",
			"drawOrder": "z-order",
			"useRenderCells": false,
			"blendMode": "normal",
			"zElevation": 0,
			"global": false
		},
		{
			"name": "water",
			"overriden": 0,
			"subLayers": [],
			"instances": [
				{
					"type": "water",
					"properties": {
						"initially-visible": true,
						"origin": "top",
						"wrap-horizontal": "repeat",
						"wrap-vertical": "clamp-to-edge",
						"image-offset-x": 0,
						"image-offset-y": 0,
						"image-scale-x": 1,
						"image-scale-y": 1,
						"image-angle": 0
					},
					"uid": 2708,
					"instanceVariables": {
						"is_ocean": true
					},
					"behaviors": {},
					"effects": {
						"Water": {
							"isEnabled": true,
							"parameters": {
								"speed": 0.1,
								"x-speed": 0.3,
								"y-speed": 0.3,
								"intensity": 1,
								"frequency": 2,
								"angle": 7,
								"delta": 20,
								"reflectivity": 15,
								"emboss": 0.15
							}
						}
					},
					"world": {
						"x": 585,
						"y": 540,
						"width": 3015,
						"height": 270,
						"originX": 0.5,
						"originY": 0,
						"color": [
							1,
							1,
							1,
							0.9629999694824218
						],
						"angle": 0,
						"zElevation": 0
					}
				}
			],
			"sid": 442525143435603,
			"effectTypes": [],
			"isInitiallyVisible": true,
			"isInitiallyInteractive": true,
			"color": [
				1,
				1,
				1,
				1
			],
			"backgroundColor": [
				1,
				1,
				1,
				1
			],
			"isTransparent": true,
			"parallaxX": 1,
			"parallaxY": 1,
			"scaleRate": 1,
			"forceOwnTexture": false,
			"renderingMode": "3d",
			"drawOrder": "z-order",
			"useRenderCells": false,
			"blendMode": "normal",
			"zElevation": 0,
			"global": false
		},
		{
			"name": "camera",
			"overriden": 0,
			"subLayers": [],
			"instances": [
				{
					"type": "camera",
					"properties": {
						"initially-visible": false,
						"initial-animation": "Animation 1",
						"initial-frame": 0,
						"enable-collisions": false,
						"live-preview": false
					},
					"uid": 2709,
					"instanceVariables": {
						"movementSpeed": 2
					},
					"behaviors": {
						"Timer": {
							"properties": {}
						},
						"Pin": {
							"properties": {
								"destroy": false
							}
						},
						"ScrollTo": {
							"properties": {
								"enabled": true
							}
						},
						"Tween": {
							"properties": {
								"enabled": false
							}
						}
					},
					"world": {
						"x": 159.83469021979712,
						"y": 252.88062797000072,
						"width": 32,
						"height": 32,
						"originX": 0.5,
						"originY": 0.5,
						"color": [
							1,
							1,
							1,
							1
						],
						"angle": 0,
						"zElevation": 0
					}
				}
			],
			"sid": 695064461162444,
			"effectTypes": [],
			"isInitiallyVisible": true,
			"isInitiallyInteractive": true,
			"color": [
				1,
				1,
				1,
				1
			],
			"backgroundColor": [
				1,
				1,
				1,
				1
			],
			"isTransparent": true,
			"parallaxX": 1,
			"parallaxY": 1,
			"scaleRate": 1,
			"forceOwnTexture": false,
			"renderingMode": "3d",
			"drawOrder": "z-order",
			"useRenderCells": false,
			"blendMode": "normal",
			"zElevation": 0,
			"global": false
		},
		{
			"name": "interface",
			"overriden": 1,
			"subLayers": [],
			"instances": [],
			"sid": 232625103413089,
			"effectTypes": [],
			"isInitiallyVisible": true,
			"isInitiallyInteractive": true,
			"color": [
				1,
				1,
				1,
				1
			],
			"backgroundColor": [
				1,
				1,
				1,
				1
			],
			"isTransparent": true,
			"parallaxX": 0,
			"parallaxY": 0,
			"scaleRate": 1,
			"forceOwnTexture": false,
			"renderingMode": "3d",
			"drawOrder": "z-order",
			"useRenderCells": false,
			"blendMode": "normal",
			"zElevation": 0,
			"global": false
		},
		{
			"name": "interface_winner_menu",
			"overriden": 1,
			"subLayers": [],
			"instances": [],
			"sid": 664159498431219,
			"effectTypes": [],
			"isInitiallyVisible": false,
			"isInitiallyInteractive": true,
			"color": [
				1,
				1,
				1,
				1
			],
			"backgroundColor": [
				1,
				1,
				1,
				1
			],
			"isTransparent": true,
			"parallaxX": 0,
			"parallaxY": 0,
			"scaleRate": 1,
			"forceOwnTexture": false,
			"renderingMode": "3d",
			"drawOrder": "z-order",
			"useRenderCells": false,
			"blendMode": "normal",
			"zElevation": 0,
			"global": false
		},
		{
			"name": "debug",
			"overriden": 1,
			"subLayers": [],
			"instances": [],
			"sid": 984276659943611,
			"effectTypes": [],
			"isInitiallyVisible": true,
			"isInitiallyInteractive": true,
			"color": [
				1,
				1,
				1,
				1
			],
			"backgroundColor": [
				1,
				1,
				1,
				1
			],
			"isTransparent": true,
			"parallaxX": 0,
			"parallaxY": 0,
			"scaleRate": 0,
			"forceOwnTexture": false,
			"renderingMode": "3d",
			"drawOrder": "z-order",
			"useRenderCells": false,
			"blendMode": "normal",
			"zElevation": 0,
			"global": false
		},
		{
			"name": "loader",
			"overriden": 1,
			"subLayers": [],
			"instances": [],
			"sid": 625465620854564,
			"effectTypes": [],
			"isInitiallyVisible": true,
			"isInitiallyInteractive": true,
			"color": [
				1,
				1,
				1,
				1
			],
			"backgroundColor": [
				0.8666666666666667,
				0.9725490196078431,
				1,
				1
			],
			"isTransparent": false,
			"parallaxX": 0,
			"parallaxY": 0,
			"scaleRate": 0,
			"forceOwnTexture": false,
			"renderingMode": "3d",
			"drawOrder": "z-order",
			"useRenderCells": false,
			"blendMode": "normal",
			"zElevation": 0,
			"global": false
		}
	],
	"sid": 123473409263111,
	"nonworld-instances": [],
	"effectTypes": [],
	"width": 1258,
	"height": 585,
	"unboundedScrolling": true,
	"vpX": 0.5,
	"vpY": 0.5,
	"projection": "perspective",
	"eventSheet": "#basic events"
}